SingletonFactory/ResourceProvider.py
SingletonFactory/__init__.py
SingletonFactory-0.0.1.dist-info/LICENSE
SingletonFactory-0.0.1.dist-info/METADATA
SingletonFactory-0.0.1.dist-info/WHEEL
SingletonFactory-0.0.1.dist-info/top_level.txt
SingletonFactory-0.0.1.dist-info/RECORD
